django_rq_dashboard/__init__.py
django_rq_dashboard/forms.py
django_rq_dashboard/models.py
django_rq_dashboard/urls.py
django_rq_dashboard/views.py
django_rq_dashboard/static/rq/jquery.js
django_rq_dashboard/static/rq/rqdashboard.js
django_rq_dashboard/static/rq/underscore.js
django_rq_dashboard/templates/rq/job.html
django_rq_dashboard/templates/rq/queue.html
django_rq_dashboard/templates/rq/queue_actions.html
django_rq_dashboard/templates/rq/scheduler.html
django_rq_dashboard/templates/rq/stats.html
django_rq_dashboard/templates/rq/worker.html
django_rq_dashboard-0.3.3.dist-info/DESCRIPTION.rst
django_rq_dashboard-0.3.3.dist-info/METADATA
django_rq_dashboard-0.3.3.dist-info/RECORD
django_rq_dashboard-0.3.3.dist-info/WHEEL
django_rq_dashboard-0.3.3.dist-info/metadata.json
django_rq_dashboard-0.3.3.dist-info/top_level.txt
