Metadata-Version: 2.0
Name: django-rq-dashboard
Version: 0.3.3
Summary: A dashboard for managing RQ in the Django admin
Home-page: https://github.com/brutasse/django-rq-dashboard
Author: Bruno Renié
Author-email: bruno@renie.fr
License: BSD licence, see LICENCE file
Platform: UNKNOWN
Classifier: Development Status :: 3 - Alpha
Classifier: Environment :: Web Environment
Classifier: Framework :: Django
Classifier: Intended Audience :: Developers
Classifier: License :: OSI Approved :: BSD License
Classifier: Natural Language :: English
Classifier: Programming Language :: Python
Classifier: Programming Language :: Python :: 2.6
Classifier: Programming Language :: Python :: 2.7
Classifier: Programming Language :: Python :: 3.3
Classifier: Programming Language :: Python :: 3.4
Classifier: Programming Language :: Python :: 3.5
Requires-Dist: Django (>=1.5)
Requires-Dist: pytz
Requires-Dist: rq
